{
  "system": "ASIOD_PAYMENT_GATEWAY",
  "version": "0.1.0",
  "purpose": "Connect ASIOD Information Bridge traffic to paid contracted access before full verification is delivered.",
  "payment_flow": [
    "receive_bridge_request",
    "return_limited_preview",
    "show_paid_service_offer",
    "collect_payment",
    "api_key_only",
    "deliver_full_correction_report",
    "issue_receipt",
    "payout_to_stripe_pay"
  ],
  "free_layer": "limited_bridge_summary_only",
  "paid_layer": "full_verification_and_receipts",
  "payment_before_full_service": true,
  "stripe_pay": "payout_destination_only",
  "private_source_exposed_publicly": false,
  "status": "PAYMENT_TO_STRIPE_PAY_ONLY"
}
